appleauth/__init__.py
appleauth/apis.py
appleauth/mixins.py
appleauth/serializers.py
appleauth/services.py
appleauth/settings.py
appleauth-0.0.1.dist-info/METADATA
appleauth-0.0.1.dist-info/LICENSE
appleauth-0.0.1.dist-info/WHEEL
appleauth-0.0.1.dist-info/RECORD
