Metadata-Version: 2.1
Name: appleauth
Version: 0.0.1
Summary: Python library to implement Sign In with Apple in your Django backend.
Home-page: https://primedigitalglobal.github.io/appleauth
License: MIT
Keywords: apple signin,apple auth
Author: Primedigital Global
Author-email: oss@primedigital.tech
Maintainer: Vikalp Jain
Maintainer-email: vikalp@primedigital.tech
Requires-Python: >=3.9,<4.0
Classifier: Development Status :: 4 - Beta
Classifier: Intended Audience :: Developers
Classifier: License :: OSI Approved :: MIT License
Classifier: Natural Language :: English
Classifier: Operating System :: OS Independent
Classifier: Programming Language :: Python :: 3
Classifier: Programming Language :: Python :: 3.9
Classifier: Programming Language :: Python :: 3.10
Classifier: Programming Language :: Python :: 3.11
Classifier: Programming Language :: Python :: 3.9
Requires-Dist: PyJWT (>=2.6.0,<3.0.0)
Requires-Dist: djangorestframework (>=3.14.0,<4.0.0)
Requires-Dist: requests (>=2.28.1,<3.0.0)
Project-URL: Documentation, https://primedigitalglobal.github.io/appleauth
Project-URL: Repository, https://github.com/PrimedigitalGlobal/appleauth
